aiom3u8downloader/__init__.py
aiom3u8downloader/aiodownloadm3u8.py
aiom3u8downloader/config.py
aiom3u8downloader/configlogger.py
aiom3u8downloader/logger.conf
aiom3u8downloader-1.1.4.dist-info/LICENSE
aiom3u8downloader-1.1.4.dist-info/METADATA
aiom3u8downloader-1.1.4.dist-info/WHEEL
aiom3u8downloader-1.1.4.dist-info/entry_points.txt
aiom3u8downloader-1.1.4.dist-info/top_level.txt
aiom3u8downloader-1.1.4.dist-info/RECORD
