Metadata-Version: 2.1
Name: aiom3u8downloader
Version: 1.1.4
Summary: Update package m3u8downloader to use aiohttp download m3u8 url
Home-page: https://github.com/kirikumo/aiom3u8downloader/
Author: cghn
License: GPLv3
Classifier: License :: OSI Approved :: GNU General Public License v3 (GPLv3)
Classifier: Programming Language :: Python :: 3.6
Requires-Python: >=3.6
License-File: LICENSE
Requires-Dist: requests (>=2.25.1)
Requires-Dist: aiohttp (>=3.8.1)
